nmos_auth-1.5.0.data/scripts/nmosauth
nmosauth/__init__.py
nmosauth/auth_server/__init__.py
nmosauth/auth_server/app.py
nmosauth/auth_server/basic_auth.py
nmosauth/auth_server/client_registration.py
nmosauth/auth_server/config.py
nmosauth/auth_server/constants.py
nmosauth/auth_server/db_utils.py
nmosauth/auth_server/handlers.py
nmosauth/auth_server/metadata.py
nmosauth/auth_server/models.py
nmosauth/auth_server/oauth2.py
nmosauth/auth_server/security_api.py
nmosauth/auth_server/security_service.py
nmosauth/auth_server/settings.py
nmosauth/auth_server/token_generator.py
nmosauth/auth_server/static/bbc_favicon.ico
nmosauth/auth_server/static/error.css
nmosauth/auth_server/static/jquery.js
nmosauth/auth_server/static/main.js
nmosauth/auth_server/static/style.css
nmosauth/auth_server/templates/authorize.html
nmosauth/auth_server/templates/create_client.html
nmosauth/auth_server/templates/error.html
nmosauth/auth_server/templates/fetch_token.html
nmosauth/auth_server/templates/home.html
nmosauth/auth_server/templates/layout.html
nmosauth/auth_server/templates/login.html
nmosauth/auth_server/templates/signup.html
nmosauth/auth_server/templates/users.html
usr/bin/nmosauth
var/nmosauth/gen_cert.py
nmos_auth-1.5.0.dist-info/LICENSE.md
nmos_auth-1.5.0.dist-info/METADATA
nmos_auth-1.5.0.dist-info/NOTICE.md
nmos_auth-1.5.0.dist-info/WHEEL
nmos_auth-1.5.0.dist-info/top_level.txt
nmos_auth-1.5.0.dist-info/RECORD
